Metadata-Version: 1.0
Name: epr
Version: 0.25
Summary: Tool for quickly adding debugging output
Home-page: https://github.com/Cogmob/epr
Author: Luke Avery
Author-email: cogmob@gmail.com
License: UNKNOWN
Platform: UNKNOWN
